dataxi/connectors/__init__.py
dataxi/connectors/mysql_connector.py
dataxi/cred_mgr/__init__.py
dataxi/cred_mgr/cred_mgr.py
dataxi/cred_mgr/cred_mgr_cli.py
dataxi/cred_mgr/cred_sender.py
dataxi/operators/__init__.py
dataxi-0.0.9.dist-info/LICENSE
dataxi-0.0.9.dist-info/METADATA
dataxi-0.0.9.dist-info/WHEEL
dataxi-0.0.9.dist-info/entry_points.txt
dataxi-0.0.9.dist-info/top_level.txt
dataxi-0.0.9.dist-info/RECORD
