Metadata-Version: 2.2
Name: dataxi
Version: 0.0.9
Summary: Dataxi is a cross-DBMS server tool that can help you centralize the data extraction and transfer from different data sources.
Author-email: Yuan Yuan <yyccphil@gmail.com>
License: MIT License
Project-URL: Project, https://github.com/yyccPhil/dataxi
Keywords: ETL
Classifier: Programming Language :: Python :: 3
Classifier: License :: OSI Approved :: MIT License
Classifier: Operating System :: OS Independent
Requires-Python: >=3.6
License-File: LICENSE
